fast_viterbi/__init__.py
fast_viterbi/__main__.py
fast_viterbi/_core.cp311-win32.pyd
fast_viterbi/_core.pyi
fast_viterbi/py.typed
fast_viterbi-0.1.2.dist-info/METADATA
fast_viterbi-0.1.2.dist-info/WHEEL
fast_viterbi-0.1.2.dist-info/licenses/LICENSE
fast_viterbi-0.1.2.dist-info/RECORD
