Metadata-Version: 2.1
Name: fast_viterbi
Version: 0.1.2
Summary: a viterbi algo collection
Author-Email: district10 <dvorak4tzx@gmail.com>
Classifier: Development Status :: 4 - Beta
Classifier: License :: OSI Approved :: MIT License
Classifier: Programming Language :: Python :: 3 :: Only
Classifier: Programming Language :: Python :: 3.7
Classifier: Programming Language :: Python :: 3.8
Classifier: Programming Language :: Python :: 3.9
Classifier: Programming Language :: Python :: 3.10
Classifier: Programming Language :: Python :: 3.11
Classifier: Programming Language :: Python :: 3.12
Requires-Python: >=3.7
Requires-Dist: fire
Requires-Dist: pytest; extra == "test"
Provides-Extra: test
